<annotation>
	<folder>New</folder>
	<filename>image556.jpg</filename>
	<path>/home/ihamed/Downloads/New/image556.jpg</path>
	<source>
		<database>Unknown</database>
	</source>
	<size>
		<width>596</width>
		<height>336</height>
		<depth>3</depth>
	</size>
	<segmented>0</segmented>
	<object>
		<name>licenseplate</name>
		<pose>Unspecified</pose>
		<truncated>0</truncated>
		<difficult>0</difficult>
		<bndbox>
			<xmin>292</xmin>
			<ymin>126</ymin>
			<xmax>337</xmax>
			<ymax>156</ymax>
		</bndbox>
	</object>
</annotation>
